{
  "artists": {
    "artist": [
      {
        "name": "Queen",
        "playcount": "182390419",
        "listeners": "3956139",
        "mbid": "420ca290-76c5-41af-999e-564d7c71f1a7",
        "url": "https://www.last.fm/music/Queen",
        "streamable": "0",
        "image": [
          {
            "#text": "https://lastfm-img2.akamaized.net/i/u/34s/97ce751da8d7461f9196bb4abf62e6d8.png",
            "size": "small"
          },
          {
            "#text": "https://lastfm-img2.akamaized.net/i/u/64s/97ce751da8d7461f9196bb4abf62e6d8.png",
            "size": "medium"
          },
          {
            "#text": "https://lastfm-img2.akamaized.net/i/u/174s/97ce751da8d7461f9196bb4abf62e6d8.png",
            "size": "large"
          },
          {
            "#text": "https://lastfm-img2.akamaized.net/i/u/300x300/97ce751da8d7461f9196bb4abf62e6d8.png",
            "size": "extralarge"
          },
          {
            "#text": "https://lastfm-img2.akamaized.net/i/u/300x300/97ce751da8d7461f9196bb4abf62e6d8.png",
            "size": "mega"
          }
        ]
      },
      {
        "name": "Ariana Grande",
        "playcount": "76213085",
        "listeners": "1003693",
        "mbid": "f4fdbb4c-e4b7-47a0-b83b-d91bbfcfa387",
        "url": "https://www.last.fm/music/Ariana+Grande",
        "streamable": "0",
        "image": [
          {
            "#text": "https://lastfm-img2.akamaized.net/i/u/34s/96d4299c199ca7a0256dcfd42c9c693d.png",
            "size": "small"
          },
          {
            "#text": "https://lastfm-img2.akamaized.net/i/u/64s/96d4299c199ca7a0256dcfd42c9c693d.png",
            "size": "medium"
          },
          {
            "#text": "https://lastfm-img2.akamaized.net/i/u/174s/96d4299c199ca7a0256dcfd42c9c693d.png",
            "size": "large"
          },
          {
            "#text": "https://lastfm-img2.akamaized.net/i/u/300x300/96d4299c199ca7a0256dcfd42c9c693d.png",
            "size": "extralarge"
          },
          {
            "#text": "https://lastfm-img2.akamaized.net/i/u/300x300/96d4299c199ca7a0256dcfd42c9c693d.png",
            "size": "mega"
          }
        ]
      },
      {
        "name": "Imagine Dragons",
        "playcount": "77024800",
        "listeners": "1617808",
        "mbid": "012151a8-0f9a-44c9-997f-ebd68b5389f9",
        "url": "https://www.last.fm/music/Imagine+Dragons",
        "streamable": "0",
        "image": [
          {
            "#text": "https://lastfm-img2.akamaized.net/i/u/34s/1708c8c2cff9b9fbdcc4722f36ad3e73.png",
            "size": "small"
          },
          {
            "#text": "https://lastfm-img2.akamaized.net/i/u/64s/1708c8c2cff9b9fbdcc4722f36ad3e73.png",
            "size": "medium"
          },
          {
            "#text": "https://lastfm-img2.akamaized.net/i/u/174s/1708c8c2cff9b9fbdcc4722f36ad3e73.png",
            "size": "large"
          },
          {
            "#text": "https://lastfm-img2.akamaized.net/i/u/300x300/1708c8c2cff9b9fbdcc4722f36ad3e73.png",
            "size": "extralarge"
          },
          {
            "#text": "https://lastfm-img2.akamaized.net/i/u/300x300/1708c8c2cff9b9fbdcc4722f36ad3e73.png",
            "size": "mega"
          }
        ]
      },
      {
        "name": "The Beatles",
        "playcount": "508472898",
        "listeners": "3628108",
        "mbid": "b10bbbfc-cf9e-42e0-be17-e2c3e1d2600d",
        "url": "https://www.last.fm/music/The+Beatles",
        "streamable": "0",
        "image": [
          {
            "#text": "https://lastfm-img2.akamaized.net/i/u/34s/047a20990f8ffd0442352e67c4e0bcdc.png",
            "size": "small"
          },
          {
            "#text": "https://lastfm-img2.akamaized.net/i/u/64s/047a20990f8ffd0442352e67c4e0bcdc.png",
            "size": "medium"
          },
          {
            "#text": "https://lastfm-img2.akamaized.net/i/u/174s/047a20990f8ffd0442352e67c4e0bcdc.png",
            "size": "large"
          },
          {
            "#text": "https://lastfm-img2.akamaized.net/i/u/300x300/047a20990f8ffd0442352e67c4e0bcdc.png",
            "size": "extralarge"
          },
          {
            "#text": "https://lastfm-img2.akamaized.net/i/u/300x300/047a20990f8ffd0442352e67c4e0bcdc.png",
            "size": "mega"
          }
        ]
      },
      {
        "name": "Arctic Monkeys",
        "playcount": "325654587",
        "listeners": "3459163",
        "mbid": "ada7a83c-e3e1-40f1-93f9-3e73dbc9298a",
        "url": "https://www.last.fm/music/Arctic+Monkeys",
        "streamable": "0",
        "image": [
          {
            "#text": "https://lastfm-img2.akamaized.net/i/u/34s/26b8728bcf3ce5c3cf0cc776cd462851.png",
            "size": "small"
          },
          {
            "#text": "https://lastfm-img2.akamaized.net/i/u/64s/26b8728bcf3ce5c3cf0cc776cd462851.png",
            "size": "medium"
          },
          {
            "#text": "https://lastfm-img2.akamaized.net/i/u/174s/26b8728bcf3ce5c3cf0cc776cd462851.png",
            "size": "large"
          },
          {
            "#text": "https://lastfm-img2.akamaized.net/i/u/300x300/26b8728bcf3ce5c3cf0cc776cd462851.png",
            "size": "extralarge"
          },
          {
            "#text": "https://lastfm-img2.akamaized.net/i/u/300x300/26b8728bcf3ce5c3cf0cc776cd462851.png",
            "size": "mega"
          }
        ]
      },
      {
        "name": "Coldplay",
        "playcount": "356185468",
        "listeners": "5338425",
        "mbid": "cc197bad-dc9c-440d-a5b5-d52ba2e14234",
        "url": "https://www.last.fm/music/Coldplay",
        "streamable": "0",
        "image": [
          {
            "#text": "https://lastfm-img2.akamaized.net/i/u/34s/421cac7d8e42662f069c4b69e7934d7b.png",
            "size": "small"
          },
          {
            "#text": "https://lastfm-img2.akamaized.net/i/u/64s/421cac7d8e42662f069c4b69e7934d7b.png",
            "size": "medium"
          },
          {
            "#text": "https://lastfm-img2.akamaized.net/i/u/174s/421cac7d8e42662f069c4b69e7934d7b.png",
            "size": "large"
          },
          {
            "#text": "https://lastfm-img2.akamaized.net/i/u/300x300/421cac7d8e42662f069c4b69e7934d7b.png",
            "size": "extralarge"
          },
          {
            "#text": "https://lastfm-img2.akamaized.net/i/u/300x300/421cac7d8e42662f069c4b69e7934d7b.png",
            "size": "mega"
          }
        ]
      },
      {
        "name": "Kanye West",
        "playcount": "229534235",
        "listeners": "4344268",
        "mbid": "164f0d73-1234-4e2c-8743-d77bf2191051",
        "url": "https://www.last.fm/music/Kanye+West",
        "streamable": "0",
        "image": [
          {
            "#text": "https://lastfm-img2.akamaized.net/i/u/34s/2e41be70d0554819c89dc8d291efa205.png",
            "size": "small"
          },
          {
            "#text": "https://lastfm-img2.akamaized.net/i/u/64s/2e41be70d0554819c89dc8d291efa205.png",
            "size": "medium"
          },
          {
            "#text": "https://lastfm-img2.akamaized.net/i/u/174s/2e41be70d0554819c89dc8d291efa205.png",
            "size": "large"
          },
          {
            "#text": "https://lastfm-img2.akamaized.net/i/u/300x300/2e41be70d0554819c89dc8d291efa205.png",
            "size": "extralarge"
          },
          {
            "#text": "https://lastfm-img2.akamaized.net/i/u/300x300/2e41be70d0554819c89dc8d291efa205.png",
            "size": "mega"
          }
        ]
      },
      {
        "name": "Radiohead",
        "playcount": "492441304",
        "listeners": "4692902",
        "mbid": "a74b1b7f-71a5-4011-9441-d0b5e4122711",
        "url": "https://www.last.fm/music/Radiohead",
        "streamable": "0",
        "image": [
          {
            "#text": "https://lastfm-img2.akamaized.net/i/u/34s/e5c21d51b912602a5ee9f5086106cbbe.png",
            "size": "small"
          },
          {
            "#text": "https://lastfm-img2.akamaized.net/i/u/64s/e5c21d51b912602a5ee9f5086106cbbe.png",
            "size": "medium"
          },
          {
            "#text": "https://lastfm-img2.akamaized.net/i/u/174s/e5c21d51b912602a5ee9f5086106cbbe.png",
            "size": "large"
          },
          {
            "#text": "https://lastfm-img2.akamaized.net/i/u/300x300/e5c21d51b912602a5ee9f5086106cbbe.png",
            "size": "extralarge"
          },
          {
            "#text": "https://lastfm-img2.akamaized.net/i/u/300x300/e5c21d51b912602a5ee9f5086106cbbe.png",
            "size": "mega"
          }
        ]
      },
      {
        "name": "David Bowie",
        "playcount": "188759081",
        "listeners": "3316475",
        "mbid": "5441c29d-3602-4898-b1a1-b77fa23b8e50",
        "url": "https://www.last.fm/music/David+Bowie",
        "streamable": "0",
        "image": [
          {
            "#text": "https://lastfm-img2.akamaized.net/i/u/34s/a7b31cd8825e40efaf37724e928a6026.png",
            "size": "small"
          },
          {
            "#text": "https://lastfm-img2.akamaized.net/i/u/64s/a7b31cd8825e40efaf37724e928a6026.png",
            "size": "medium"
          },
          {
            "#text": "https://lastfm-img2.akamaized.net/i/u/174s/a7b31cd8825e40efaf37724e928a6026.png",
            "size": "large"
          },
          {
            "#text": "https://lastfm-img2.akamaized.net/i/u/300x300/a7b31cd8825e40efaf37724e928a6026.png",
            "size": "extralarge"
          },
          {
            "#text": "https://lastfm-img2.akamaized.net/i/u/300x300/a7b31cd8825e40efaf37724e928a6026.png",
            "size": "mega"
          }
        ]
      },
      {
        "name": "Lady Gaga",
        "playcount": "276756415",
        "listeners": "3760612",
        "mbid": "650e7db6-b795-4eb5-a702-5ea2fc46c848",
        "url": "https://www.last.fm/music/Lady+Gaga",
        "streamable": "0",
        "image": [
          {
            "#text": "https://lastfm-img2.akamaized.net/i/u/34s/7e60fbde56b666051778546a6c230659.png",
            "size": "small"
          },
          {
            "#text": "https://lastfm-img2.akamaized.net/i/u/64s/7e60fbde56b666051778546a6c230659.png",
            "size": "medium"
          },
          {
            "#text": "https://lastfm-img2.akamaized.net/i/u/174s/7e60fbde56b666051778546a6c230659.png",
            "size": "large"
          },
          {
            "#text": "https://lastfm-img2.akamaized.net/i/u/300x300/7e60fbde56b666051778546a6c230659.png",
            "size": "extralarge"
          },
          {
            "#text": "https://lastfm-img2.akamaized.net/i/u/300x300/7e60fbde56b666051778546a6c230659.png",
            "size": "mega"
          }
        ]
      },
      {
        "name": "Drake",
        "playcount": "134378358",
        "listeners": "3331667",
        "mbid": "b49b81cc-d5b7-4bdd-aadb-385df8de69a6",
        "url": "https://www.last.fm/music/Drake",
        "streamable": "0",
        "image": [
          {
            "#text": "https://lastfm-img2.akamaized.net/i/u/34s/94e1fa3f4df90e2ab9dd540bd336d015.png",
            "size": "small"
          },
          {
            "#text": "https://lastfm-img2.akamaized.net/i/u/64s/94e1fa3f4df90e2ab9dd540bd336d015.png",
            "size": "medium"
          },
          {
            "#text": "https://lastfm-img2.akamaized.net/i/u/174s/94e1fa3f4df90e2ab9dd540bd336d015.png",
            "size": "large"
          },
          {
            "#text": "https://lastfm-img2.akamaized.net/i/u/300x300/94e1fa3f4df90e2ab9dd540bd336d015.png",
            "size": "extralarge"
          },
          {
            "#text": "https://lastfm-img2.akamaized.net/i/u/300x300/94e1fa3f4df90e2ab9dd540bd336d015.png",
            "size": "mega"
          }
        ]
      },
      {
        "name": "Muse",
        "playcount": "340806924",
        "listeners": "4060596",
        "mbid": "fd857293-5ab8-40de-b29e-55a69d4e4d0f",
        "url": "https://www.last.fm/music/Muse",
        "streamable": "0",
        "image": [
          {
            "#text": "https://lastfm-img2.akamaized.net/i/u/34s/aa8f114a226084388391008cd40d86c3.png",
            "size": "small"
          },
          {
            "#text": "https://lastfm-img2.akamaized.net/i/u/64s/aa8f114a226084388391008cd40d86c3.png",
            "size": "medium"
          },
          {
            "#text": "https://lastfm-img2.akamaized.net/i/u/174s/aa8f114a226084388391008cd40d86c3.png",
            "size": "large"
          },
          {
            "#text": "https://lastfm-img2.akamaized.net/i/u/300x300/aa8f114a226084388391008cd40d86c3.png",
            "size": "extralarge"
          },
          {
            "#text": "https://lastfm-img2.akamaized.net/i/u/300x300/aa8f114a226084388391008cd40d86c3.png",
            "size": "mega"
          }
        ]
      },
      {
        "name": "Kendrick Lamar",
        "playcount": "95837555",
        "listeners": "1422548",
        "mbid": "381086ea-f511-4aba-bdf9-71c753dc5077",
        "url": "https://www.last.fm/music/Kendrick+Lamar",
        "streamable": "0",
        "image": [
          {
            "#text": "https://lastfm-img2.akamaized.net/i/u/34s/63d1fd1856256d77b6443a67d4264982.png",
            "size": "small"
          },
          {
            "#text": "https://lastfm-img2.akamaized.net/i/u/64s/63d1fd1856256d77b6443a67d4264982.png",
            "size": "medium"
          },
          {
            "#text": "https://lastfm-img2.akamaized.net/i/u/174s/63d1fd1856256d77b6443a67d4264982.png",
            "size": "large"
          },
          {
            "#text": "https://lastfm-img2.akamaized.net/i/u/300x300/63d1fd1856256d77b6443a67d4264982.png",
            "size": "extralarge"
          },
          {
            "#text": "https://lastfm-img2.akamaized.net/i/u/300x300/63d1fd1856256d77b6443a67d4264982.png",
            "size": "mega"
          }
        ]
      },
      {
        "name": "Rihanna",
        "playcount": "194869853",
        "listeners": "4510143",
        "mbid": "db36a76f-4cdf-43ac-8cd0-5e48092d2bae",
        "url": "https://www.last.fm/music/Rihanna",
        "streamable": "0",
        "image": [
          {
            "#text": "https://lastfm-img2.akamaized.net/i/u/34s/6b6b670c2a1fc02e39ef2b4a638e98cf.png",
            "size": "small"
          },
          {
            "#text": "https://lastfm-img2.akamaized.net/i/u/64s/6b6b670c2a1fc02e39ef2b4a638e98cf.png",
            "size": "medium"
          },
          {
            "#text": "https://lastfm-img2.akamaized.net/i/u/174s/6b6b670c2a1fc02e39ef2b4a638e98cf.png",
            "size": "large"
          },
          {
            "#text": "https://lastfm-img2.akamaized.net/i/u/300x300/6b6b670c2a1fc02e39ef2b4a638e98cf.png",
            "size": "extralarge"
          },
          {
            "#text": "https://lastfm-img2.akamaized.net/i/u/300x300/6b6b670c2a1fc02e39ef2b4a638e98cf.png",
            "size": "mega"
          }
        ]
      },
      {
        "name": "Sia",
        "playcount": "77168933",
        "listeners": "2079586",
        "mbid": "2f548675-008d-4332-876c-108b0c7ab9c5",
        "url": "https://www.last.fm/music/Sia",
        "streamable": "0",
        "image": [
          {
            "#text": "https://lastfm-img2.akamaized.net/i/u/34s/056f956d41ce3d5fddab01685f31c4c3.png",
            "size": "small"
          },
          {
            "#text": "https://lastfm-img2.akamaized.net/i/u/64s/056f956d41ce3d5fddab01685f31c4c3.png",
            "size": "medium"
          },
          {
            "#text": "https://lastfm-img2.akamaized.net/i/u/174s/056f956d41ce3d5fddab01685f31c4c3.png",
            "size": "large"
          },
          {
            "#text": "https://lastfm-img2.akamaized.net/i/u/300x300/056f956d41ce3d5fddab01685f31c4c3.png",
            "size": "extralarge"
          },
          {
            "#text": "https://lastfm-img2.akamaized.net/i/u/300x300/056f956d41ce3d5fddab01685f31c4c3.png",
            "size": "mega"
          }
        ]
      },
      {
        "name": "Calvin Harris",
        "playcount": "70917979",
        "listeners": "2148336",
        "mbid": "8dd98bdc-80ec-4e93-8509-2f46bafc09a7",
        "url": "https://www.last.fm/music/Calvin+Harris",
        "streamable": "0",
        "image": [
          {
            "#text": "https://lastfm-img2.akamaized.net/i/u/34s/ca83997a225a4368eb55f82717add274.png",
            "size": "small"
          },
          {
            "#text": "https://lastfm-img2.akamaized.net/i/u/64s/ca83997a225a4368eb55f82717add274.png",
            "size": "medium"
          },
          {
            "#text": "https://lastfm-img2.akamaized.net/i/u/174s/ca83997a225a4368eb55f82717add274.png",
            "size": "large"
          },
          {
            "#text": "https://lastfm-img2.akamaized.net/i/u/300x300/ca83997a225a4368eb55f82717add274.png",
            "size": "extralarge"
          },
          {
            "#text": "https://lastfm-img2.akamaized.net/i/u/300x300/ca83997a225a4368eb55f82717add274.png",
            "size": "mega"
          }
        ]
      },
      {
        "name": "Red Hot Chili Peppers",
        "playcount": "289625991",
        "listeners": "4582866",
        "mbid": "8bfac288-ccc5-448d-9573-c33ea2aa5c30",
        "url": "https://www.last.fm/music/Red+Hot+Chili+Peppers",
        "streamable": "0",
        "image": [
          {
            "#text": "https://lastfm-img2.akamaized.net/i/u/34s/cada75a68530403d83c971b0bfd26edf.png",
            "size": "small"
          },
          {
            "#text": "https://lastfm-img2.akamaized.net/i/u/64s/cada75a68530403d83c971b0bfd26edf.png",
            "size": "medium"
          },
          {
            "#text": "https://lastfm-img2.akamaized.net/i/u/174s/cada75a68530403d83c971b0bfd26edf.png",
            "size": "large"
          },
          {
            "#text": "https://lastfm-img2.akamaized.net/i/u/300x300/cada75a68530403d83c971b0bfd26edf.png",
            "size": "extralarge"
          },
          {
            "#text": "https://lastfm-img2.akamaized.net/i/u/300x300/cada75a68530403d83c971b0bfd26edf.png",
            "size": "mega"
          }
        ]
      },
      {
        "name": "Post Malone",
        "playcount": "19278800",
        "listeners": "480182",
        "mbid": "",
        "url": "https://www.last.fm/music/Post+Malone",
        "streamable": "0",
        "image": [
          {
            "#text": "https://lastfm-img2.akamaized.net/i/u/34s/26a5047063cee0ec5f96ecd05e9885d8.png",
            "size": "small"
          },
          {
            "#text": "https://lastfm-img2.akamaized.net/i/u/64s/26a5047063cee0ec5f96ecd05e9885d8.png",
            "size": "medium"
          },
          {
            "#text": "https://lastfm-img2.akamaized.net/i/u/174s/26a5047063cee0ec5f96ecd05e9885d8.png",
            "size": "large"
          },
          {
            "#text": "https://lastfm-img2.akamaized.net/i/u/300x300/26a5047063cee0ec5f96ecd05e9885d8.png",
            "size": "extralarge"
          },
          {
            "#text": "https://lastfm-img2.akamaized.net/i/u/300x300/26a5047063cee0ec5f96ecd05e9885d8.png",
            "size": "mega"
          }
        ]
      },
      {
        "name": "Eminem",
        "playcount": "194520562",
        "listeners": "4474513",
        "mbid": "b95ce3ff-3d05-4e87-9e01-c97b66af13d4",
        "url": "https://www.last.fm/music/Eminem",
        "streamable": "0",
        "image": [
          {
            "#text": "https://lastfm-img2.akamaized.net/i/u/34s/278dcdfa0d82469f959bff53d8c97579.png",
            "size": "small"
          },
          {
            "#text": "https://lastfm-img2.akamaized.net/i/u/64s/278dcdfa0d82469f959bff53d8c97579.png",
            "size": "medium"
          },
          {
            "#text": "https://lastfm-img2.akamaized.net/i/u/174s/278dcdfa0d82469f959bff53d8c97579.png",
            "size": "large"
          },
          {
            "#text": "https://lastfm-img2.akamaized.net/i/u/300x300/278dcdfa0d82469f959bff53d8c97579.png",
            "size": "extralarge"
          },
          {
            "#text": "https://lastfm-img2.akamaized.net/i/u/300x300/278dcdfa0d82469f959bff53d8c97579.png",
            "size": "mega"
          }
        ]
      },
      {
        "name": "Lana Del Rey",
        "playcount": "209502848",
        "listeners": "1838927",
        "mbid": "b7539c32-53e7-4908-bda3-81449c367da6",
        "url": "https://www.last.fm/music/Lana+Del+Rey",
        "streamable": "0",
        "image": [
          {
            "#text": "https://lastfm-img2.akamaized.net/i/u/34s/84dd5413ac2654b644945f0da879a52c.png",
            "size": "small"
          },
          {
            "#text": "https://lastfm-img2.akamaized.net/i/u/64s/84dd5413ac2654b644945f0da879a52c.png",
            "size": "medium"
          },
          {
            "#text": "https://lastfm-img2.akamaized.net/i/u/174s/84dd5413ac2654b644945f0da879a52c.png",
            "size": "large"
          },
          {
            "#text": "https://lastfm-img2.akamaized.net/i/u/300x300/84dd5413ac2654b644945f0da879a52c.png",
            "size": "extralarge"
          },
          {
            "#text": "https://lastfm-img2.akamaized.net/i/u/300x300/84dd5413ac2654b644945f0da879a52c.png",
            "size": "mega"
          }
        ]
      },
      {
        "name": "Billie Eilish",
        "playcount": "7961158",
        "listeners": "291197",
        "mbid": "",
        "url": "https://www.last.fm/music/Billie+Eilish",
        "streamable": "0",
        "image": [
          {
            "#text": "https://lastfm-img2.akamaized.net/i/u/34s/8b879acb5c75bfdc02ce4f90ac3866a3.png",
            "size": "small"
          },
          {
            "#text": "https://lastfm-img2.akamaized.net/i/u/64s/8b879acb5c75bfdc02ce4f90ac3866a3.png",
            "size": "medium"
          },
          {
            "#text": "https://lastfm-img2.akamaized.net/i/u/174s/8b879acb5c75bfdc02ce4f90ac3866a3.png",
            "size": "large"
          },
          {
            "#text": "https://lastfm-img2.akamaized.net/i/u/300x300/8b879acb5c75bfdc02ce4f90ac3866a3.png",
            "size": "extralarge"
          },
          {
            "#text": "https://lastfm-img2.akamaized.net/i/u/300x300/8b879acb5c75bfdc02ce4f90ac3866a3.png",
            "size": "mega"
          }
        ]
      },
      {
        "name": "Pink Floyd",
        "playcount": "308194428",
        "listeners": "3043463",
        "mbid": "83d91898-7763-47d7-b03b-b92132375c47",
        "url": "https://www.last.fm/music/Pink+Floyd",
        "streamable": "0",
        "image": [
          {
            "#text": "https://lastfm-img2.akamaized.net/i/u/34s/dabfc686f9414917aff605a1d6d12758.png",
            "size": "small"
          },
          {
            "#text": "https://lastfm-img2.akamaized.net/i/u/64s/dabfc686f9414917aff605a1d6d12758.png",
            "size": "medium"
          },
          {
            "#text": "https://lastfm-img2.akamaized.net/i/u/174s/dabfc686f9414917aff605a1d6d12758.png",
            "size": "large"
          },
          {
            "#text": "https://lastfm-img2.akamaized.net/i/u/300x300/dabfc686f9414917aff605a1d6d12758.png",
            "size": "extralarge"
          },
          {
            "#text": "https://lastfm-img2.akamaized.net/i/u/300x300/dabfc686f9414917aff605a1d6d12758.png",
            "size": "mega"
          }
        ]
      },
      {
        "name": "The Weeknd",
        "playcount": "73173340",
        "listeners": "1228724",
        "mbid": "c8b03190-306c-4120-bb0b-6f2ebfc06ea9",
        "url": "https://www.last.fm/music/The+Weeknd",
        "streamable": "0",
        "image": [
          {
            "#text": "https://lastfm-img2.akamaized.net/i/u/34s/8760735bd8a8e5e56dc2f863555eae07.png",
            "size": "small"
          },
          {
            "#text": "https://lastfm-img2.akamaized.net/i/u/64s/8760735bd8a8e5e56dc2f863555eae07.png",
            "size": "medium"
          },
          {
            "#text": "https://lastfm-img2.akamaized.net/i/u/174s/8760735bd8a8e5e56dc2f863555eae07.png",
            "size": "large"
          },
          {
            "#text": "https://lastfm-img2.akamaized.net/i/u/300x300/8760735bd8a8e5e56dc2f863555eae07.png",
            "size": "extralarge"
          },
          {
            "#text": "https://lastfm-img2.akamaized.net/i/u/300x300/8760735bd8a8e5e56dc2f863555eae07.png",
            "size": "mega"
          }
        ]
      },
      {
        "name": "Mariah Carey",
        "playcount": "70059679",
        "listeners": "2405972",
        "mbid": "494e8d09-f85b-4543-892f-a5096aed1cd4",
        "url": "https://www.last.fm/music/Mariah+Carey",
        "streamable": "0",
        "image": [
          {
            "#text": "https://lastfm-img2.akamaized.net/i/u/34s/94e53cb2ea84a37cc5b2ba6acc6d6dd8.png",
            "size": "small"
          },
          {
            "#text": "https://lastfm-img2.akamaized.net/i/u/64s/94e53cb2ea84a37cc5b2ba6acc6d6dd8.png",
            "size": "medium"
          },
          {
            "#text": "https://lastfm-img2.akamaized.net/i/u/174s/94e53cb2ea84a37cc5b2ba6acc6d6dd8.png",
            "size": "large"
          },
          {
            "#text": "https://lastfm-img2.akamaized.net/i/u/300x300/94e53cb2ea84a37cc5b2ba6acc6d6dd8.png",
            "size": "extralarge"
          },
          {
            "#text": "https://lastfm-img2.akamaized.net/i/u/300x300/94e53cb2ea84a37cc5b2ba6acc6d6dd8.png",
            "size": "mega"
          }
        ]
      },
      {
        "name": "Nirvana",
        "playcount": "219089194",
        "listeners": "4232247",
        "mbid": "9282c8b4-ca0b-4c6b-b7e3-4f7762dfc4d6",
        "url": "https://www.last.fm/music/Nirvana",
        "streamable": "0",
        "image": [
          {
            "#text": "https://lastfm-img2.akamaized.net/i/u/34s/a054709103c5cff66a25681d5822c8bf.png",
            "size": "small"
          },
          {
            "#text": "https://lastfm-img2.akamaized.net/i/u/64s/a054709103c5cff66a25681d5822c8bf.png",
            "size": "medium"
          },
          {
            "#text": "https://lastfm-img2.akamaized.net/i/u/174s/a054709103c5cff66a25681d5822c8bf.png",
            "size": "large"
          },
          {
            "#text": "https://lastfm-img2.akamaized.net/i/u/300x300/a054709103c5cff66a25681d5822c8bf.png",
            "size": "extralarge"
          },
          {
            "#text": "https://lastfm-img2.akamaized.net/i/u/300x300/a054709103c5cff66a25681d5822c8bf.png",
            "size": "mega"
          }
        ]
      },
      {
        "name": "Ed Sheeran",
        "playcount": "82435896",
        "listeners": "1580152",
        "mbid": "b8a7c51f-362c-4dcb-a259-bc6e0095f0a6",
        "url": "https://www.last.fm/music/Ed+Sheeran",
        "streamable": "0",
        "image": [
          {
            "#text": "https://lastfm-img2.akamaized.net/i/u/34s/fa36962445080a3357cd1585fd2cb474.png",
            "size": "small"
          },
          {
            "#text": "https://lastfm-img2.akamaized.net/i/u/64s/fa36962445080a3357cd1585fd2cb474.png",
            "size": "medium"
          },
          {
            "#text": "https://lastfm-img2.akamaized.net/i/u/174s/fa36962445080a3357cd1585fd2cb474.png",
            "size": "large"
          },
          {
            "#text": "https://lastfm-img2.akamaized.net/i/u/300x300/fa36962445080a3357cd1585fd2cb474.png",
            "size": "extralarge"
          },
          {
            "#text": "https://lastfm-img2.akamaized.net/i/u/300x300/fa36962445080a3357cd1585fd2cb474.png",
            "size": "mega"
          }
        ]
      },
      {
        "name": "Fleetwood Mac",
        "playcount": "64856258",
        "listeners": "2112002",
        "mbid": "bd13909f-1c29-4c27-a874-d4aaf27c5b1a",
        "url": "https://www.last.fm/music/Fleetwood+Mac",
        "streamable": "0",
        "image": [
          {
            "#text": "https://lastfm-img2.akamaized.net/i/u/34s/2c102767857e449598a978a23c90b443.png",
            "size": "small"
          },
          {
            "#text": "https://lastfm-img2.akamaized.net/i/u/64s/2c102767857e449598a978a23c90b443.png",
            "size": "medium"
          },
          {
            "#text": "https://lastfm-img2.akamaized.net/i/u/174s/2c102767857e449598a978a23c90b443.png",
            "size": "large"
          },
          {
            "#text": "https://lastfm-img2.akamaized.net/i/u/300x300/2c102767857e449598a978a23c90b443.png",
            "size": "extralarge"
          },
          {
            "#text": "https://lastfm-img2.akamaized.net/i/u/300x300/2c102767857e449598a978a23c90b443.png",
            "size": "mega"
          }
        ]
      },
      {
        "name": "Dua Lipa",
        "playcount": "19627829",
        "listeners": "461126",
        "mbid": "",
        "url": "https://www.last.fm/music/Dua+Lipa",
        "streamable": "0",
        "image": [
          {
            "#text": "https://lastfm-img2.akamaized.net/i/u/34s/0f0aa8861e9d273553da5a1b4ff7409d.png",
            "size": "small"
          },
          {
            "#text": "https://lastfm-img2.akamaized.net/i/u/64s/0f0aa8861e9d273553da5a1b4ff7409d.png",
            "size": "medium"
          },
          {
            "#text": "https://lastfm-img2.akamaized.net/i/u/174s/0f0aa8861e9d273553da5a1b4ff7409d.png",
            "size": "large"
          },
          {
            "#text": "https://lastfm-img2.akamaized.net/i/u/300x300/0f0aa8861e9d273553da5a1b4ff7409d.png",
            "size": "extralarge"
          },
          {
            "#text": "https://lastfm-img2.akamaized.net/i/u/300x300/0f0aa8861e9d273553da5a1b4ff7409d.png",
            "size": "mega"
          }
        ]
      },
      {
        "name": "The Rolling Stones",
        "playcount": "151687881",
        "listeners": "3763834",
        "mbid": "b071f9fa-14b0-4217-8e97-eb41da73f598",
        "url": "https://www.last.fm/music/The+Rolling+Stones",
        "streamable": "0",
        "image": [
          {
            "#text": "https://lastfm-img2.akamaized.net/i/u/34s/37fd85b836984fb287d4d7f006315eb3.png",
            "size": "small"
          },
          {
            "#text": "https://lastfm-img2.akamaized.net/i/u/64s/37fd85b836984fb287d4d7f006315eb3.png",
            "size": "medium"
          },
          {
            "#text": "https://lastfm-img2.akamaized.net/i/u/174s/37fd85b836984fb287d4d7f006315eb3.png",
            "size": "large"
          },
          {
            "#text": "https://lastfm-img2.akamaized.net/i/u/300x300/37fd85b836984fb287d4d7f006315eb3.png",
            "size": "extralarge"
          },
          {
            "#text": "https://lastfm-img2.akamaized.net/i/u/300x300/37fd85b836984fb287d4d7f006315eb3.png",
            "size": "mega"
          }
        ]
      },
      {
        "name": "The Killers",
        "playcount": "206390449",
        "listeners": "4390263",
        "mbid": "95e1ead9-4d31-4808-a7ac-32c3614c116b",
        "url": "https://www.last.fm/music/The+Killers",
        "streamable": "0",
        "image": [
          {
            "#text": "https://lastfm-img2.akamaized.net/i/u/34s/6583c8519c5393cbfdaf860f8bf6d68a.png",
            "size": "small"
          },
          {
            "#text": "https://lastfm-img2.akamaized.net/i/u/64s/6583c8519c5393cbfdaf860f8bf6d68a.png",
            "size": "medium"
          },
          {
            "#text": "https://lastfm-img2.akamaized.net/i/u/174s/6583c8519c5393cbfdaf860f8bf6d68a.png",
            "size": "large"
          },
          {
            "#text": "https://lastfm-img2.akamaized.net/i/u/300x300/6583c8519c5393cbfdaf860f8bf6d68a.png",
            "size": "extralarge"
          },
          {
            "#text": "https://lastfm-img2.akamaized.net/i/u/300x300/6583c8519c5393cbfdaf860f8bf6d68a.png",
            "size": "mega"
          }
        ]
      },
      {
        "name": "Gorillaz",
        "playcount": "166878656",
        "listeners": "3543990",
        "mbid": "e21857d5-3256-4547-afb3-4b6ded592596",
        "url": "https://www.last.fm/music/Gorillaz",
        "streamable": "0",
        "image": [
          {
            "#text": "https://lastfm-img2.akamaized.net/i/u/34s/0952986399f240b374badfb5499791b8.png",
            "size": "small"
          },
          {
            "#text": "https://lastfm-img2.akamaized.net/i/u/64s/0952986399f240b374badfb5499791b8.png",
            "size": "medium"
          },
          {
            "#text": "https://lastfm-img2.akamaized.net/i/u/174s/0952986399f240b374badfb5499791b8.png",
            "size": "large"
          },
          {
            "#text": "https://lastfm-img2.akamaized.net/i/u/300x300/0952986399f240b374badfb5499791b8.png",
            "size": "extralarge"
          },
          {
            "#text": "https://lastfm-img2.akamaized.net/i/u/300x300/0952986399f240b374badfb5499791b8.png",
            "size": "mega"
          }
        ]
      },
      {
        "name": "Linkin Park",
        "playcount": "289519925",
        "listeners": "3944143",
        "mbid": "f59c5520-5f46-4d2c-b2c4-822eabf53419",
        "url": "https://www.last.fm/music/Linkin+Park",
        "streamable": "0",
        "image": [
          {
            "#text": "https://lastfm-img2.akamaized.net/i/u/34s/8425d15256d9702ef5d611210a6d2709.png",
            "size": "small"
          },
          {
            "#text": "https://lastfm-img2.akamaized.net/i/u/64s/8425d15256d9702ef5d611210a6d2709.png",
            "size": "medium"
          },
          {
            "#text": "https://lastfm-img2.akamaized.net/i/u/174s/8425d15256d9702ef5d611210a6d2709.png",
            "size": "large"
          },
          {
            "#text": "https://lastfm-img2.akamaized.net/i/u/300x300/8425d15256d9702ef5d611210a6d2709.png",
            "size": "extralarge"
          },
          {
            "#text": "https://lastfm-img2.akamaized.net/i/u/300x300/8425d15256d9702ef5d611210a6d2709.png",
            "size": "mega"
          }
        ]
      },
      {
        "name": "Maroon 5",
        "playcount": "116118562",
        "listeners": "3468193",
        "mbid": "0ab49580-c84f-44d4-875f-d83760ea2cfe",
        "url": "https://www.last.fm/music/Maroon+5",
        "streamable": "0",
        "image": [
          {
            "#text": "https://lastfm-img2.akamaized.net/i/u/34s/d060b61e7bbd463a94f6326a034abfb7.png",
            "size": "small"
          },
          {
            "#text": "https://lastfm-img2.akamaized.net/i/u/64s/d060b61e7bbd463a94f6326a034abfb7.png",
            "size": "medium"
          },
          {
            "#text": "https://lastfm-img2.akamaized.net/i/u/174s/d060b61e7bbd463a94f6326a034abfb7.png",
            "size": "large"
          },
          {
            "#text": "https://lastfm-img2.akamaized.net/i/u/300x300/d060b61e7bbd463a94f6326a034abfb7.png",
            "size": "extralarge"
          },
          {
            "#text": "https://lastfm-img2.akamaized.net/i/u/300x300/d060b61e7bbd463a94f6326a034abfb7.png",
            "size": "mega"
          }
        ]
      },
      {
        "name": "Childish Gambino",
        "playcount": "47486944",
        "listeners": "882859",
        "mbid": "7fb57fba-a6ef-44c2-abab-2fa3bdee607e",
        "url": "https://www.last.fm/music/Childish+Gambino",
        "streamable": "0",
        "image": [
          {
            "#text": "https://lastfm-img2.akamaized.net/i/u/34s/e05954de969f3851cdedb80d964501ef.png",
            "size": "small"
          },
          {
            "#text": "https://lastfm-img2.akamaized.net/i/u/64s/e05954de969f3851cdedb80d964501ef.png",
            "size": "medium"
          },
          {
            "#text": "https://lastfm-img2.akamaized.net/i/u/174s/e05954de969f3851cdedb80d964501ef.png",
            "size": "large"
          },
          {
            "#text": "https://lastfm-img2.akamaized.net/i/u/300x300/e05954de969f3851cdedb80d964501ef.png",
            "size": "extralarge"
          },
          {
            "#text": "https://lastfm-img2.akamaized.net/i/u/300x300/e05954de969f3851cdedb80d964501ef.png",
            "size": "mega"
          }
        ]
      },
      {
        "name": "Panic! at the Disco",
        "playcount": "106300294",
        "listeners": "2139045",
        "mbid": "b9472588-93f3-4922-a1a2-74082cdf9ce8",
        "url": "https://www.last.fm/music/Panic%21+at+the+Disco",
        "streamable": "0",
        "image": [
          {
            "#text": "https://lastfm-img2.akamaized.net/i/u/34s/4ead0ac5109ea30d109b4ef90868c2ab.png",
            "size": "small"
          },
          {
            "#text": "https://lastfm-img2.akamaized.net/i/u/64s/4ead0ac5109ea30d109b4ef90868c2ab.png",
            "size": "medium"
          },
          {
            "#text": "https://lastfm-img2.akamaized.net/i/u/174s/4ead0ac5109ea30d109b4ef90868c2ab.png",
            "size": "large"
          },
          {
            "#text": "https://lastfm-img2.akamaized.net/i/u/300x300/4ead0ac5109ea30d109b4ef90868c2ab.png",
            "size": "extralarge"
          },
          {
            "#text": "https://lastfm-img2.akamaized.net/i/u/300x300/4ead0ac5109ea30d109b4ef90868c2ab.png",
            "size": "mega"
          }
        ]
      },
      {
        "name": "Clean Bandit",
        "playcount": "15820208",
        "listeners": "803651",
        "mbid": "dacc2d64-7e59-42a8-87a9-10c53919aff2",
        "url": "https://www.last.fm/music/Clean+Bandit",
        "streamable": "0",
        "image": [
          {
            "#text": "https://lastfm-img2.akamaized.net/i/u/34s/7ea45d5906c6a3f427d4af2a52666834.png",
            "size": "small"
          },
          {
            "#text": "https://lastfm-img2.akamaized.net/i/u/64s/7ea45d5906c6a3f427d4af2a52666834.png",
            "size": "medium"
          },
          {
            "#text": "https://lastfm-img2.akamaized.net/i/u/174s/7ea45d5906c6a3f427d4af2a52666834.png",
            "size": "large"
          },
          {
            "#text": "https://lastfm-img2.akamaized.net/i/u/300x300/7ea45d5906c6a3f427d4af2a52666834.png",
            "size": "extralarge"
          },
          {
            "#text": "https://lastfm-img2.akamaized.net/i/u/300x300/7ea45d5906c6a3f427d4af2a52666834.png",
            "size": "mega"
          }
        ]
      },
      {
        "name": "Taylor Swift",
        "playcount": "162850628",
        "listeners": "2161236",
        "mbid": "20244d07-534f-4eff-b4d4-930878889970",
        "url": "https://www.last.fm/music/Taylor+Swift",
        "streamable": "0",
        "image": [
          {
            "#text": "https://lastfm-img2.akamaized.net/i/u/34s/0c7cb7913d8c3eea9f1a4b5426393cdb.png",
            "size": "small"
          },
          {
            "#text": "https://lastfm-img2.akamaized.net/i/u/64s/0c7cb7913d8c3eea9f1a4b5426393cdb.png",
            "size": "medium"
          },
          {
            "#text": "https://lastfm-img2.akamaized.net/i/u/174s/0c7cb7913d8c3eea9f1a4b5426393cdb.png",
            "size": "large"
          },
          {
            "#text": "https://lastfm-img2.akamaized.net/i/u/300x300/0c7cb7913d8c3eea9f1a4b5426393cdb.png",
            "size": "extralarge"
          },
          {
            "#text": "https://lastfm-img2.akamaized.net/i/u/300x300/0c7cb7913d8c3eea9f1a4b5426393cdb.png",
            "size": "mega"
          }
        ]
      },
      {
        "name": "Led Zeppelin",
        "playcount": "185534880",
        "listeners": "2894417",
        "mbid": "d6e0e274-8e19-44ce-b5b2-52c12f8a674a",
        "url": "https://www.last.fm/music/Led+Zeppelin",
        "streamable": "0",
        "image": [
          {
            "#text": "https://lastfm-img2.akamaized.net/i/u/34s/fa2755753b15f1c2380a7796351ecd08.png",
            "size": "small"
          },
          {
            "#text": "https://lastfm-img2.akamaized.net/i/u/64s/fa2755753b15f1c2380a7796351ecd08.png",
            "size": "medium"
          },
          {
            "#text": "https://lastfm-img2.akamaized.net/i/u/174s/fa2755753b15f1c2380a7796351ecd08.png",
            "size": "large"
          },
          {
            "#text": "https://lastfm-img2.akamaized.net/i/u/300x300/fa2755753b15f1c2380a7796351ecd08.png",
            "size": "extralarge"
          },
          {
            "#text": "https://lastfm-img2.akamaized.net/i/u/300x300/fa2755753b15f1c2380a7796351ecd08.png",
            "size": "mega"
          }
        ]
      },
      {
        "name": "Michael Jackson",
        "playcount": "128719196",
        "listeners": "3504344",
        "mbid": "f27ec8db-af05-4f36-916e-3d57f91ecf5e",
        "url": "https://www.last.fm/music/Michael+Jackson",
        "streamable": "0",
        "image": [
          {
            "#text": "https://lastfm-img2.akamaized.net/i/u/34s/b67c724c33abc559a472d64995de76db.png",
            "size": "small"
          },
          {
            "#text": "https://lastfm-img2.akamaized.net/i/u/64s/b67c724c33abc559a472d64995de76db.png",
            "size": "medium"
          },
          {
            "#text": "https://lastfm-img2.akamaized.net/i/u/174s/b67c724c33abc559a472d64995de76db.png",
            "size": "large"
          },
          {
            "#text": "https://lastfm-img2.akamaized.net/i/u/300x300/b67c724c33abc559a472d64995de76db.png",
            "size": "extralarge"
          },
          {
            "#text": "https://lastfm-img2.akamaized.net/i/u/300x300/b67c724c33abc559a472d64995de76db.png",
            "size": "mega"
          }
        ]
      },
      {
        "name": "Halsey",
        "playcount": "23293041",
        "listeners": "502707",
        "mbid": "",
        "url": "https://www.last.fm/music/Halsey",
        "streamable": "0",
        "image": [
          {
            "#text": "https://lastfm-img2.akamaized.net/i/u/34s/4d05e37841081faee9c940b9c089b2b5.png",
            "size": "small"
          },
          {
            "#text": "https://lastfm-img2.akamaized.net/i/u/64s/4d05e37841081faee9c940b9c089b2b5.png",
            "size": "medium"
          },
          {
            "#text": "https://lastfm-img2.akamaized.net/i/u/174s/4d05e37841081faee9c940b9c089b2b5.png",
            "size": "large"
          },
          {
            "#text": "https://lastfm-img2.akamaized.net/i/u/300x300/4d05e37841081faee9c940b9c089b2b5.png",
            "size": "extralarge"
          },
          {
            "#text": "https://lastfm-img2.akamaized.net/i/u/300x300/4d05e37841081faee9c940b9c089b2b5.png",
            "size": "mega"
          }
        ]
      },
      {
        "name": "xxxtentacion",
        "playcount": "16494577",
        "listeners": "287522",
        "mbid": "",
        "url": "https://www.last.fm/music/xxxtentacion",
        "streamable": "0",
        "image": [
          {
            "#text": "https://lastfm-img2.akamaized.net/i/u/34s/fc441b7fdda27bbbfb985a9010285a2c.png",
            "size": "small"
          },
          {
            "#text": "https://lastfm-img2.akamaized.net/i/u/64s/fc441b7fdda27bbbfb985a9010285a2c.png",
            "size": "medium"
          },
          {
            "#text": "https://lastfm-img2.akamaized.net/i/u/174s/fc441b7fdda27bbbfb985a9010285a2c.png",
            "size": "large"
          },
          {
            "#text": "https://lastfm-img2.akamaized.net/i/u/300x300/fc441b7fdda27bbbfb985a9010285a2c.png",
            "size": "extralarge"
          },
          {
            "#text": "https://lastfm-img2.akamaized.net/i/u/300x300/fc441b7fdda27bbbfb985a9010285a2c.png",
            "size": "mega"
          }
        ]
      },
      {
        "name": "Travi$ Scott",
        "playcount": "26094935",
        "listeners": "373425",
        "mbid": "e4a51f17-a57b-47b1-b37b-f552d0f8e9e6",
        "url": "https://www.last.fm/music/Travi$+Scott",
        "streamable": "0",
        "image": [
          {
            "#text": "https://lastfm-img2.akamaized.net/i/u/34s/217d669d3699818789e9e30ef406c58f.png",
            "size": "small"
          },
          {
            "#text": "https://lastfm-img2.akamaized.net/i/u/64s/217d669d3699818789e9e30ef406c58f.png",
            "size": "medium"
          },
          {
            "#text": "https://lastfm-img2.akamaized.net/i/u/174s/217d669d3699818789e9e30ef406c58f.png",
            "size": "large"
          },
          {
            "#text": "https://lastfm-img2.akamaized.net/i/u/300x300/217d669d3699818789e9e30ef406c58f.png",
            "size": "extralarge"
          },
          {
            "#text": "https://lastfm-img2.akamaized.net/i/u/300x300/217d669d3699818789e9e30ef406c58f.png",
            "size": "mega"
          }
        ]
      },
      {
        "name": "Lorde",
        "playcount": "68144270",
        "listeners": "1214492",
        "mbid": "8e494408-8620-4c6a-82c2-c2ca4a1e4f12",
        "url": "https://www.last.fm/music/Lorde",
        "streamable": "0",
        "image": [
          {
            "#text": "https://lastfm-img2.akamaized.net/i/u/34s/e6201e8a9499cc9fbedb9947af262c79.png",
            "size": "small"
          },
          {
            "#text": "https://lastfm-img2.akamaized.net/i/u/64s/e6201e8a9499cc9fbedb9947af262c79.png",
            "size": "medium"
          },
          {
            "#text": "https://lastfm-img2.akamaized.net/i/u/174s/e6201e8a9499cc9fbedb9947af262c79.png",
            "size": "large"
          },
          {
            "#text": "https://lastfm-img2.akamaized.net/i/u/300x300/e6201e8a9499cc9fbedb9947af262c79.png",
            "size": "extralarge"
          },
          {
            "#text": "https://lastfm-img2.akamaized.net/i/u/300x300/e6201e8a9499cc9fbedb9947af262c79.png",
            "size": "mega"
          }
        ]
      },
      {
        "name": "David Guetta",
        "playcount": "86987753",
        "listeners": "2744025",
        "mbid": "302bd7b9-d012-4360-897a-93b00c855680",
        "url": "https://www.last.fm/music/David+Guetta",
        "streamable": "0",
        "image": [
          {
            "#text": "https://lastfm-img2.akamaized.net/i/u/34s/17d74dbec15abf6b11f25b0eb54d58ab.png",
            "size": "small"
          },
          {
            "#text": "https://lastfm-img2.akamaized.net/i/u/64s/17d74dbec15abf6b11f25b0eb54d58ab.png",
            "size": "medium"
          },
          {
            "#text": "https://lastfm-img2.akamaized.net/i/u/174s/17d74dbec15abf6b11f25b0eb54d58ab.png",
            "size": "large"
          },
          {
            "#text": "https://lastfm-img2.akamaized.net/i/u/300x300/17d74dbec15abf6b11f25b0eb54d58ab.png",
            "size": "extralarge"
          },
          {
            "#text": "https://lastfm-img2.akamaized.net/i/u/300x300/17d74dbec15abf6b11f25b0eb54d58ab.png",
            "size": "mega"
          }
        ]
      },
      {
        "name": "Daft Punk",
        "playcount": "207136283",
        "listeners": "3749246",
        "mbid": "056e4f3e-d505-4dad-8ec1-d04f521cbb56",
        "url": "https://www.last.fm/music/Daft+Punk",
        "streamable": "0",
        "image": [
          {
            "#text": "https://lastfm-img2.akamaized.net/i/u/34s/9fd718d4c80e4ac89107c6c0bb908440.png",
            "size": "small"
          },
          {
            "#text": "https://lastfm-img2.akamaized.net/i/u/64s/9fd718d4c80e4ac89107c6c0bb908440.png",
            "size": "medium"
          },
          {
            "#text": "https://lastfm-img2.akamaized.net/i/u/174s/9fd718d4c80e4ac89107c6c0bb908440.png",
            "size": "large"
          },
          {
            "#text": "https://lastfm-img2.akamaized.net/i/u/300x300/9fd718d4c80e4ac89107c6c0bb908440.png",
            "size": "extralarge"
          },
          {
            "#text": "https://lastfm-img2.akamaized.net/i/u/300x300/9fd718d4c80e4ac89107c6c0bb908440.png",
            "size": "mega"
          }
        ]
      },
      {
        "name": "Metallica",
        "playcount": "275010224",
        "listeners": "2864271",
        "mbid": "65f4f0c5-ef9e-490c-aee3-909e7ae6b2ab",
        "url": "https://www.last.fm/music/Metallica",
        "streamable": "0",
        "image": [
          {
            "#text": "https://lastfm-img2.akamaized.net/i/u/34s/22fffa33531b4684a4eb269d357758ae.png",
            "size": "small"
          },
          {
            "#text": "https://lastfm-img2.akamaized.net/i/u/64s/22fffa33531b4684a4eb269d357758ae.png",
            "size": "medium"
          },
          {
            "#text": "https://lastfm-img2.akamaized.net/i/u/174s/22fffa33531b4684a4eb269d357758ae.png",
            "size": "large"
          },
          {
            "#text": "https://lastfm-img2.akamaized.net/i/u/300x300/22fffa33531b4684a4eb269d357758ae.png",
            "size": "extralarge"
          },
          {
            "#text": "https://lastfm-img2.akamaized.net/i/u/300x300/22fffa33531b4684a4eb269d357758ae.png",
            "size": "mega"
          }
        ]
      },
      {
        "name": "Tame Impala",
        "playcount": "69051109",
        "listeners": "1078945",
        "mbid": "63aa26c3-d59b-4da4-84ac-716b54f1ef4d",
        "url": "https://www.last.fm/music/Tame+Impala",
        "streamable": "0",
        "image": [
          {
            "#text": "https://lastfm-img2.akamaized.net/i/u/34s/12a2bbc58ad344fab891686d6eb88889.png",
            "size": "small"
          },
          {
            "#text": "https://lastfm-img2.akamaized.net/i/u/64s/12a2bbc58ad344fab891686d6eb88889.png",
            "size": "medium"
          },
          {
            "#text": "https://lastfm-img2.akamaized.net/i/u/174s/12a2bbc58ad344fab891686d6eb88889.png",
            "size": "large"
          },
          {
            "#text": "https://lastfm-img2.akamaized.net/i/u/300x300/12a2bbc58ad344fab891686d6eb88889.png",
            "size": "extralarge"
          },
          {
            "#text": "https://lastfm-img2.akamaized.net/i/u/300x300/12a2bbc58ad344fab891686d6eb88889.png",
            "size": "mega"
          }
        ]
      },
      {
        "name": "The Cure",
        "playcount": "153352660",
        "listeners": "2898316",
        "mbid": "69ee3720-a7cb-4402-b48d-a02c366f2bcf",
        "url": "https://www.last.fm/music/The+Cure",
        "streamable": "0",
        "image": [
          {
            "#text": "https://lastfm-img2.akamaized.net/i/u/34s/0adefe283018c0b7a743f6c1149fc54e.png",
            "size": "small"
          },
          {
            "#text": "https://lastfm-img2.akamaized.net/i/u/64s/0adefe283018c0b7a743f6c1149fc54e.png",
            "size": "medium"
          },
          {
            "#text": "https://lastfm-img2.akamaized.net/i/u/174s/0adefe283018c0b7a743f6c1149fc54e.png",
            "size": "large"
          },
          {
            "#text": "https://lastfm-img2.akamaized.net/i/u/300x300/0adefe283018c0b7a743f6c1149fc54e.png",
            "size": "extralarge"
          },
          {
            "#text": "https://lastfm-img2.akamaized.net/i/u/300x300/0adefe283018c0b7a743f6c1149fc54e.png",
            "size": "mega"
          }
        ]
      },
      {
        "name": "The Chainsmokers",
        "playcount": "18746393",
        "listeners": "750146",
        "mbid": "91a81925-92f9-4fc9-b897-93cf01226282",
        "url": "https://www.last.fm/music/The+Chainsmokers",
        "streamable": "0",
        "image": [
          {
            "#text": "https://lastfm-img2.akamaized.net/i/u/34s/2b2db61472e1c0e0e093f272a1fe7aff.png",
            "size": "small"
          },
          {
            "#text": "https://lastfm-img2.akamaized.net/i/u/64s/2b2db61472e1c0e0e093f272a1fe7aff.png",
            "size": "medium"
          },
          {
            "#text": "https://lastfm-img2.akamaized.net/i/u/174s/2b2db61472e1c0e0e093f272a1fe7aff.png",
            "size": "large"
          },
          {
            "#text": "https://lastfm-img2.akamaized.net/i/u/300x300/2b2db61472e1c0e0e093f272a1fe7aff.png",
            "size": "extralarge"
          },
          {
            "#text": "https://lastfm-img2.akamaized.net/i/u/300x300/2b2db61472e1c0e0e093f272a1fe7aff.png",
            "size": "mega"
          }
        ]
      },
      {
        "name": "Twenty One Pilots",
        "playcount": "42151583",
        "listeners": "717192",
        "mbid": "a6c6897a-7415-4f8d-b5a5-3a5e05f3be67",
        "url": "https://www.last.fm/music/Twenty+One+Pilots",
        "streamable": "0",
        "image": [
          {
            "#text": "https://lastfm-img2.akamaized.net/i/u/34s/102ec2dabda5bde30a65063d2045a985.png",
            "size": "small"
          },
          {
            "#text": "https://lastfm-img2.akamaized.net/i/u/64s/102ec2dabda5bde30a65063d2045a985.png",
            "size": "medium"
          },
          {
            "#text": "https://lastfm-img2.akamaized.net/i/u/174s/102ec2dabda5bde30a65063d2045a985.png",
            "size": "large"
          },
          {
            "#text": "https://lastfm-img2.akamaized.net/i/u/300x300/102ec2dabda5bde30a65063d2045a985.png",
            "size": "extralarge"
          },
          {
            "#text": "https://lastfm-img2.akamaized.net/i/u/300x300/102ec2dabda5bde30a65063d2045a985.png",
            "size": "mega"
          }
        ]
      }
    ],
    "@attr": {
      "page": "1",
      "perPage": "50",
      "totalPages": "58906",
      "total": "2945283"
    }
  }
}
